business_use/__init__.py
business_use/batch.py
business_use/client.py
business_use/models.py
business_use/py.typed
business_use-0.4.1.dist-info/METADATA
business_use-0.4.1.dist-info/WHEEL
business_use-0.4.1.dist-info/RECORD
