Metadata-Version: 2.4
Name: business-use
Version: 0.4.1
Summary: Lightweight Python SDK for Business-Use event tracking and assertions
Project-URL: Homepage, https://github.com/desplega-ai/business-use
Project-URL: Documentation, https://github.com/desplega-ai/business-use#readme
Project-URL: Repository, https://github.com/desplega-ai/business-use
Project-URL: Issues, https://github.com/desplega-ai/business-use/issues
Author-email: Desplega AI <contact@desplega.ai>
Maintainer-email: Desplega AI <contact@desplega.ai>
License: MIT
Keywords: automation,event-driven,observability,testing,workflow
Classifier: Development Status :: 3 - Alpha
Classifier: Intended Audience :: Developers
Classifier: License :: OSI Approved :: MIT License
Classifier: Programming Language :: Python :: 3
Classifier: Programming Language :: Python :: 3.11
Classifier: Programming Language :: Python :: 3.12
Classifier: Programming Language :: Python :: 3.13
Classifier: Topic :: Software Development :: Libraries :: Python Modules
Classifier: Topic :: Software Development :: Testing
Requires-Python: >=3.11
Requires-Dist: httpx>=0.27.0
Requires-Dist: pydantic>=2.0.0
